j2express/__init__.py
j2express/cli.py
j2express-0.5.0.dist-info/entry_points.txt
j2express-0.5.0.dist-info/LICENSE
j2express-0.5.0.dist-info/WHEEL
j2express-0.5.0.dist-info/METADATA
j2express-0.5.0.dist-info/RECORD
