Metadata-Version: 2.1
Name: j2express
Version: 0.5.0
Summary: CLI for Jinja2 written from the ground up
Requires-Python: >=3.9
Requires-Dist: click>=8.1
Requires-Dist: Jinja2>=3.1.2
